safe_rlhf/__init__.py
safe_rlhf/logger.py
safe_rlhf/utils.py
safe_rlhf/version.py
safe_rlhf/algorithms/__init__.py
safe_rlhf/algorithms/dpo/__init__.py
safe_rlhf/algorithms/dpo/__main__.py
safe_rlhf/algorithms/dpo/main.py
safe_rlhf/algorithms/dpo/trainer.py
safe_rlhf/algorithms/ppo/__init__.py
safe_rlhf/algorithms/ppo/__main__.py
safe_rlhf/algorithms/ppo/main.py
safe_rlhf/algorithms/ppo/trainer.py
safe_rlhf/algorithms/ppo_lag/__init__.py
safe_rlhf/algorithms/ppo_lag/__main__.py
safe_rlhf/algorithms/ppo_lag/main.py
safe_rlhf/algorithms/ppo_lag/trainer.py
safe_rlhf/algorithms/ppo_reward_shaping/__init__.py
safe_rlhf/algorithms/ppo_reward_shaping/__main__.py
safe_rlhf/algorithms/ppo_reward_shaping/main.py
safe_rlhf/algorithms/ppo_reward_shaping/trainer.py
safe_rlhf/configs/__init__.py
safe_rlhf/configs/constants.py
safe_rlhf/configs/deepspeed_config.py
safe_rlhf/configs/ds_eval_config_template.json
safe_rlhf/configs/ds_train_config_template.json
safe_rlhf/configs/fsdp_config.json
safe_rlhf/datasets/__init__.py
safe_rlhf/datasets/base.py
safe_rlhf/datasets/preference.py
safe_rlhf/datasets/prompt_only.py
safe_rlhf/datasets/safety_preference.py
safe_rlhf/datasets/supervised.py
safe_rlhf/datasets/utils.py
safe_rlhf/datasets/raw/__init__.py
safe_rlhf/datasets/raw/alpaca.py
safe_rlhf/datasets/raw/firefly.py
safe_rlhf/datasets/raw/hh_rlhf.py
safe_rlhf/datasets/raw/moss.py
safe_rlhf/datasets/raw/safe_rlhf.py
safe_rlhf/evaluate/__init__.py
safe_rlhf/evaluate/arena.py
safe_rlhf/evaluate/cost.py
safe_rlhf/evaluate/reward.py
safe_rlhf/evaluate/bigbench/__init__.py
safe_rlhf/evaluate/bigbench/__main__.py
safe_rlhf/evaluate/bigbench/eval.py
safe_rlhf/evaluate/bigbench/model.py
safe_rlhf/evaluate/gpt4/__init__.py
safe_rlhf/evaluate/gpt4/__main__.py
safe_rlhf/evaluate/gpt4/eval.py
safe_rlhf/evaluate/gpt4/problem.json
safe_rlhf/finetune/__init__.py
safe_rlhf/finetune/__main__.py
safe_rlhf/finetune/deepspeed.py
safe_rlhf/finetune/huggingface.py
safe_rlhf/finetune/main.py
shtec_rlhf-1.0.5.dist-info/LICENSE
shtec_rlhf-1.0.5.dist-info/METADATA
shtec_rlhf-1.0.5.dist-info/WHEEL
shtec_rlhf-1.0.5.dist-info/top_level.txt
shtec_rlhf-1.0.5.dist-info/RECORD
